src/data_mem.v
`ifndef DATA_MEM_H
`define DATA_MEM_H

// addr here is 32 bits from BUS byt only 16 LSB bits will be used
module DataMemory(
    input wire clk,
    input wire reset,
    input wire MemWrite,
    input wire [31:0] addr,
    input wire WriteData,
    output wire [31:0] ReadData
);

// 16-bit address bus
reg [31:0] memory [2**16-1:0];
integer i;
always@(posedge clk or posedge reset) begin
    if(reset) for(i=0;i<2**16-1;i=i+1) memory[i] <= 32'd0;
    else if(MemWrite == 1'b1) memory[addr[15:0]] <= WriteData;
end
assign ReadData = memory[addr[15:0]];
endmodule

`endif

src/alu_controller.v
`ifndef ALU_CONROLLER_V
`define ALU_CONROLLER_V

module ALUController(
    input wire [6:0] opcode,
    input wire [2:0] funct3,
    input wire [6:0] funct7,
    output reg [2:0] alu_control
);

always@(*) begin
    alu_control = 7'bzzzzzzz;
    // TODO: make ALU independent of opcode, I accidentally did
    if(opcode == 7'b0110011 | opcode == 7'b0010011) begin
        case(funct3)
        3'h0: alu_control = (funct7==7'h20)?(3'b001):(3'b000); // SUB:ADD
        3'h7: alu_control = 3'b010; // AND
        3'h6: alu_control = 3'b011; // OR
        3'h4: alu_control = 3'b100; // XOR
        3'h1: alu_control = 3'b110; // SLL
        3'h5: alu_control = 3'b101; // SRL
        endcase
    end
end

endmodule

`endif

src/controller.v
`ifndef CONTROLLER_V
`define CONTROLLER_V

module Controller(
    input wire [6:0] opcode,
    input wire [6:0] funct7,
    input wire [2:0] funct3,
    input wire alu_zero,
    
    output reg RegSrc,
    output reg PCSrc,
    output reg ResultSrc,
    output reg ALUSrc,
    output reg [2:0] ImmSrc,
    output reg RegWrite,
    output reg MemWrite,
    output reg Branch
);

always@(*) begin
    case(opcode)
    7'b0110011: begin // R-Type
        RegWrite = 1'b1;
        ALUSrc = 1'b0;
        PCSrc = 1'b0;
        MemWrite = 1'b0;
        ResultSrc = 1'b0;
    end
    7'b0010011: begin // I-Type
        ImmSrc = 3'b000; 
        RegWrite = 1'b1;
        ALUSrc = 1'b1;
        MemWrite = 1'b0;
        ResultSrc = 1'b0;
        PCSrc = 1'b0;
    end
    7'b1100011: begin // B-Type
        RegWrite = 1'b0;
        MemWrite = 1'b0;
        ImmSrc = 3'b010;
        ALUSrc = 1'b0;
        // separate beq and bne
        if(funct3 == 3'h0) PCSrc = alu_zero; // beq
        else if(funct3 == 3'h1) PCSrc = ~alu_zero; // bne
        ResultSrc = 1'b0;
    end
    7'b1101111: begin // jal
        RegWrite = 1'b0;
        MemWrite = 1'b0;
        PCSrc = 1'b1;
        ImmSrc = 3'b100;
        ALUSrc = 1'b0;
        ResultSrc = 1'b0;
    end
    endcase
end

endmodule

`endif

src/alu.v
`ifndef ALU_V
`define ALU_V

module ALU(
    input wire [31:0] srcA, srcB,
    input wire [2:0] ALUControl,
    output wire alu_zero,
    output reg [31:0] alu_result
);

always@(*) begin
    alu_result = 32'd0;
    case(ALUControl)
    3'b000: alu_result = srcA+srcB;
    3'b001: alu_result = srcA-srcB;
    3'b010: alu_result = srcA&srcB;
    3'b011: alu_result = srcA|srcB;
    3'b100: alu_result = srcA^srcB;
    3'b101: alu_result = srcA>>srcB;
    3'b110: alu_result = srcA<<srcB;
    // 3'b111: Shift Right Arithemetic 
    endcase
end

assign alu_zero = (alu_result == 32'd0);

endmodule

`endif

src/sign_extend.v
`ifndef SIGN_EXT_V
`define SIGN_EXT_V

// Sign extension for jump instruction is ignored as of now

module SignExtend(
    input wire [31:7] instruction,
    input wire [2:0] ImmSrc,
    output wire [31:0] out
);

reg [31:0] out_t;
always@(*) begin
    out_t = 32'd0;
    case(ImmSrc)
        3'b000: // I-type
            out_t = { {20{instruction[31]}}, instruction[31:20] }; // 12 bits encoded
        3'b001: // S-type
            out_t = { {20{instruction[31]}}, instruction[31:25], instruction[4:0] };
        3'b010: // B-type, 12 bit encoded 1-12, 0th aways = 0
            out_t = { {19{instruction[31]}}, instruction[31], instruction[30:25], instruction[11:8], instruction[7], 1'b0 };
        3'b011: // U-type
            out_t = { instruction[31:12], 12'b0 };
        3'b100: // J-type
            out_t = { {10{instruction[20]}} ,instruction[20], instruction[19:12], instruction[20], instruction[30:21], 1'b0 };

    endcase
end

assign out = out_t;
endmodule

`endif

src/mux.v
`ifndef MUX_V
`define MUX_V

module MUX2 #(parameter size = 32)(
    input wire [size-1:0] I0,
    input wire [size-1:0] I1,
    input wire s,
    output wire [size-1:0] out
);
assign out = s?I1:I0;
endmodule

`endif

src/reg_file.v
`ifndef REG_FILE_V
`define REG_FILE_V

module RegisterFile(
    input wire clk,
    input wire reset,
    input wire RegWrite,
    input wire [4:0] addr1,
    input wire [4:0] addr2,
    input wire [4:0] addr3,
    output wire [31:0] read1,
    output wire [31:0] read2,
    output wire [31:0] data
);

reg [31:0] registers [31:0];
integer i;
always@(posedge clk or posedge reset) begin
    if(reset) for(i=0;i<32;i=i+1) registers[i] <= 32'd0;
    else if(RegWrite) registers[addr3] <= data;
    $writememh("../bin/registers.hex", registers);
end
assign read1 = registers[addr1];
assign read2 = registers[addr2];

endmodule

`endif

src/instr_mem.v
`ifndef INSTR_MEM_V
`define INSTR_MEM_V

// PC is 16-bit
module InstructionMemory(
    input wire [15:0] addr,
    output wire [31:0] instruction
);

reg [31:0] memory [2**16-1:0];
assign instruction = memory[addr];

initial $readmemh("../examples/instructions.hex", memory, 0, 6);

endmodule

`endif

src/pc.v
`ifndef PC_V
`define PC_V

// 16-bit Program Counter
module ProgramCounter(
    input wire clk,
    input wire reset,
    input wire [15:0] pc_next,
    output reg [15:0] pc
);
always@(posedge clk or posedge reset) begin
   if(reset) pc <= 15'd0;
   else pc <= pc_next;
end
endmodule

`endif

src/datapath.v
`ifndef DATAPATH_V
`define DATAPATH_V

`include "mux.v"
`include "pc.v"
`include "instr_mem.v"
`include "reg_file.v"
`include "sign_extend.v"
`include "alu.v"

module Datapath(
    input wire clk,
    input wire reset,
    output wire [15:0] PC, // goes to instruction memory
    output wire alu_zero,
    // control inputs
    input wire RegSrc,
    input wire PCSrc,
    input wire ResultSrc,
    input wire [2:0] ALUControl,
    input wire ALUSrc,
    input wire [2:0] ImmSrc,
    input wire RegWrite,
    input wire Branch,
    input wire [31:0] ReadData,
    output wire [31:0] WriteData,
    output wire [15:0] DataAddr,
    output wire [31:0] instr
);

wire [15:0] PC_Next;

wire [31:0] instruction;
wire [31:0] alu_src_a, alu_src_b;
wire [31:0] SigmImm;
wire [31:0] alu_result;
wire [31:0] Result; // goes to wd3 (register file writing data)

// wanna use only LSB 16 bits of sigimm since pc in 16 bti
MUX2 #(.size(16)) pc_mux(
    .I0(PC[15:0]+16'd4),
    .I1(PC[15:0]+SigmImm), // sigimm pehls se hi address dega, to direct add krenge
    .s(PCSrc),
    .out(PC_Next)
);

// use PC[15:2] to load instructions from memory
ProgramCounter progr_counter(
    .clk(clk), .reset(reset),
    .pc_next(PC_Next),
    .pc(PC)
);

InstructionMemory instr_mem(
    .addr(PC>>2),
    .instruction(instruction)
);

MUX2 #(.size(32)) result_mux(
    .I0(alu_result),
    .I1(ReadData),
    .s(ResultSrc),
    .out(Result)
);

RegisterFile reg_file(
    .clk(clk), .reset(reset),
    .RegWrite(RegWrite),
    .addr1(instruction[19:15]),
    .addr2(instruction[24:20]),
    .addr3(instruction[11:7]),
    .read1(alu_src_a),
    .read2(WriteData),
    .data(Result)
);

MUX2 #(.size(32)) alu_src_b_mux(
    .I0(WriteData),
    .I1(SigmImm),
    .s(ALUSrc),
    .out(alu_src_b)
);

SignExtend sign_ext(
    .instruction(instruction[31:7]),
    .ImmSrc(ImmSrc),
    .out(SigmImm)
);

ALU main_alu(
    .srcA(alu_src_a),
    .srcB(alu_src_b),
    .alu_zero(alu_zero),
    .alu_result(alu_result),
    .ALUControl(ALUControl)
);

assign DataAddr = alu_result[15:0];
assign instr = instruction;

endmodule

`endif

src/cpu.v
`ifndef CPU_V
`define CPU_V

`include "data_mem.v"
`include "instr_mem.v"
`include "controller.v"
`include "alu_controller.v"
`include "datapath.v"

module CPU(
    input wire clk,
    input wire reset
);

wire [15:0] PC;
wire alu_zero, RegSrc, PCSrc, ResultSrc, ALUSrc, RegWrite, Branch;
wire [2:0] ALUControl, ImmSrc;
wire [15:0] DataAddr;
wire [31:0] ReadData, WriteData;
wire [31:0] instruction;

Datapath datapath(
    .clk(clk), .reset(reset),
    .PC(PC),
    .alu_zero(alu_zero),
    .RegSrc(RegSrc),
    .PCSrc(PCSrc),
    .ResultSrc(ResultSrc),
    .ALUControl(ALUControl),
    .ALUSrc(ALUSrc),
    .ImmSrc(ImmSrc),
    .RegWrite(RegWrite),
    .Branch(Branch),
    .ReadData(ReadData),
    .WriteData(WriteData),
    .DataAddr(DataAddr),
    .instr(instruction)
);

Controller controller(
    .opcode(instruction[6:0]),
    .funct7(instruction[31:25]),
    .funct3(instruction[14:12]),
    .alu_zero(alu_zero),
    .RegSrc(RegSrc),
    .PCSrc(PCSrc),
    .ResultSrc(ResultSrc),
    .ALUSrc(ALUSrc),
    .ImmSrc(ImmSrc),
    .RegWrite(RegWrite),
    .MemWrite(MemWrite),
    .Branch(Branch)
);

ALUController alu_controller(
    .opcode(instruction[6:0]),
    .funct3(instruction[14:12]),
    .funct7(instruction[31:25]),
    .alu_control(ALUControl)
);

endmodule

`endif

src/cpu_tb.v
`timescale 1ns/1ps
`include "cpu.v"

module CPU_tb();

reg clk, reset;

CPU DUT(clk, reset);

initial begin
    $dumpfile("../bin/cpu.vcd");
    $dumpvars(0, DUT);
    clk = 0;
    reset = 1;
    #5 reset = 0;
    #500 $finish;
end

always #2 clk = ~clk;

endmodule

bin/cpu.vcd
$date
	Thu Jul 31 02:57:47 2025
$end
$version
	Icarus Verilog
$end
$timescale
	1ps
$end
$scope module CPU_tb $end
$scope module DUT $end
$var wire 32 ! ReadData [31:0] $end
$var wire 1 " clk $end
$var wire 1 # reset $end
$var wire 32 $ instruction [31:0] $end
$var wire 1 % alu_zero $end
$var wire 32 & WriteData [31:0] $end
$var wire 1 ' ResultSrc $end
$var wire 1 ( RegWrite $end
$var wire 1 ) RegSrc $end
$var wire 1 * PCSrc $end
$var wire 16 + PC [15:0] $end
$var wire 1 , MemWrite $end
$var wire 3 - ImmSrc [2:0] $end
$var wire 16 . DataAddr [15:0] $end
$var wire 1 / Branch $end
$var wire 1 0 ALUSrc $end
$var wire 3 1 ALUControl [2:0] $end
$scope module alu_controller $end
$var wire 3 2 funct3 [2:0] $end
$var wire 7 3 funct7 [6:0] $end
$var wire 7 4 opcode [6:0] $end
$var reg 3 5 alu_control [2:0] $end
$upscope $end
$scope module controller $end
$var wire 3 6 funct3 [2:0] $end
$var wire 7 7 funct7 [6:0] $end
$var wire 7 8 opcode [6:0] $end
$var wire 1 % alu_zero $end
$var reg 1 0 ALUSrc $end
$var reg 1 / Branch $end
$var reg 3 9 ImmSrc [2:0] $end
$var reg 1 , MemWrite $end
$var reg 1 * PCSrc $end
$var reg 1 ) RegSrc $end
$var reg 1 ( RegWrite $end
$var reg 1 ' ResultSrc $end
$upscope $end
$scope module datapath $end
$var wire 3 : ALUControl [2:0] $end
$var wire 1 0 ALUSrc $end
$var wire 1 / Branch $end
$var wire 3 ; ImmSrc [2:0] $end
$var wire 1 * PCSrc $end
$var wire 32 < ReadData [31:0] $end
$var wire 1 ) RegSrc $end
$var wire 1 ( RegWrite $end
$var wire 1 ' ResultSrc $end
$var wire 1 " clk $end
$var wire 32 = instr [31:0] $end
$var wire 1 # reset $end
$var wire 32 > instruction [31:0] $end
$var wire 1 % alu_zero $end
$var wire 32 ? alu_src_b [31:0] $end
$var wire 32 @ alu_src_a [31:0] $end
$var wire 32 A alu_result [31:0] $end
$var wire 32 B WriteData [31:0] $end
$var wire 32 C SigmImm [31:0] $end
$var wire 32 D Result [31:0] $end
$var wire 16 E PC_Next [15:0] $end
$var wire 16 F PC [15:0] $end
$var wire 16 G DataAddr [15:0] $end
$scope module alu_src_b_mux $end
$var wire 1 0 s $end
$var wire 32 H out [31:0] $end
$var wire 32 I I1 [31:0] $end
$var wire 32 J I0 [31:0] $end
$var parameter 32 K size $end
$upscope $end
$scope module instr_mem $end
$var wire 16 L addr [15:0] $end
$var wire 32 M instruction [31:0] $end
$upscope $end
$scope module main_alu $end
$var wire 3 N ALUControl [2:0] $end
$var wire 32 O srcB [31:0] $end
$var wire 32 P srcA [31:0] $end
$var wire 1 % alu_zero $end
$var reg 32 Q alu_result [31:0] $end
$upscope $end
$scope module pc_mux $end
$var wire 16 R I0 [15:0] $end
$var wire 16 S I1 [15:0] $end
$var wire 1 * s $end
$var wire 16 T out [15:0] $end
$var parameter 32 U size $end
$upscope $end
$scope module progr_counter $end
$var wire 1 " clk $end
$var wire 16 V pc_next [15:0] $end
$var wire 1 # reset $end
$var reg 16 W pc [15:0] $end
$upscope $end
$scope module reg_file $end
$var wire 1 ( RegWrite $end
$var wire 5 X addr1 [4:0] $end
$var wire 5 Y addr2 [4:0] $end
$var wire 5 Z addr3 [4:0] $end
$var wire 1 " clk $end
$var wire 32 [ read1 [31:0] $end
$var wire 32 \ read2 [31:0] $end
$var wire 1 # reset $end
$var wire 32 ] data [31:0] $end
$var integer 32 ^ i [31:0] $end
$upscope $end
$scope module result_mux $end
$var wire 32 _ I0 [31:0] $end
$var wire 32 ` I1 [31:0] $end
$var wire 1 ' s $end
$var wire 32 a out [31:0] $end
$var parameter 32 b size $end
$upscope $end
$scope module sign_ext $end
$var wire 3 c ImmSrc [2:0] $end
$var wire 25 d instruction [31:7] $end
$var wire 32 e out [31:0] $end
$var reg 32 f out_t [31:0] $end
$upscope $end
$upscope $end
$upscope $end
$upscope $end
$enddefinitions $end
$comment Show the parameter values. $end
$dumpall
b100000 b
b10000 U
b100000 K
$end
#0
$dumpvars
b0 f
b0 e
b1000 d
b0 c
b0 a
bz `
b0 _
b100000 ^
b0 ]
b0 \
b0 [
b1000 Z
b0 Y
b0 X
b0 W
b100 V
b100 T
b0 S
b100 R
b0 Q
b0 P
b0 O
b0 N
b10000010011 M
b0 L
b0 J
b0 I
b0 H
b0 G
b0 F
b100 E
b0 D
b0 C
b0 B
b0 A
b0 @
b0 ?
b10000010011 >
b10000010011 =
bz <
b0 ;
b0 :
b0 9
b10011 8
b0 7
b0 6
b0 5
b10011 4
b0 3
b0 2
b0 1
10
x/
b0 .
b0 -
0,
b0 +
0*
x)
1(
0'
b0 &
1%
b10000010011 $
1#
0"
bz !
$end
#2000
b100000 ^
1"
#4000
0"
#5000
0#
#6000
b100 D
b100 ]
b100 a
b100 .
b100 G
0%
b100 A
b100 Q
b100 _
b100 ?
b100 H
b100 O
b100 C
b100 I
b100 e
b100 f
b1000000000001001 d
b1001 Z
b100 Y
b10000000000010010010011 $
b10000000000010010010011 =
b10000000000010010010011 >
b10000000000010010010011 M
b1 L
b1000 S
b1000 E
b1000 T
b1000 V
b1000 R
b100 +
b100 F
b100 W
1"
#8000
0"
#10000
b1 D
b1 ]
b1 a
b1 .
b1 G
0%
b1 A
b1 Q
b1 _
b1 ?
b1 H
b1 O
b1 C
b1 I
b1 e
b1 f
b10000000010010 d
b10010 Z
b1 Y
b100000000100100010011 $
b100000000100100010011 =
b100000000100100010011 >
b100000000100100010011 M
b10 L
b1001 S
b1100 E
b1100 T
b1100 V
b1100 R
b1000 +
b1000 F
b1000 W
1"
#12000
0"
#14000
b100 D
b100 ]
b100 a
b100 .
b100 G
0%
b100 A
b100 Q
b100 _
b100 ?
b100 H
b100 O
b1001 C
b1001 I
b1001 e
b1001 f
b0 1
b0 5
b0 :
b0 N
00
b10010100000001000 d
b1000 Z
b100 &
b100 B
b100 J
b100 \
b1001 Y
b1000 X
b110011 4
b110011 8
b100101000000010000110011 $
b100101000000010000110011 =
b100101000000010000110011 >
b100101000000010000110011 M
b11 L
b10101 S
b10000 E
b10000 T
b10000 V
b10000 R
b1100 +
b1100 F
b1100 W
1"
#16000
0"
#18000
b10000010010 C
b10000010010 I
b10000010010 e
b10000010010 f
b1 ?
b1 H
b1 O
b1 1
b1 5
b1 :
b1 N
b11 D
b11 ]
b11 a
b11 .
b11 G
b100000100100100100001001 d
b1001 Z
b1 &
b1 B
b1 J
b1 \
b10010 Y
b1001 X
b100000 3
b100000 7
0%
b11 A
b11 Q
b11 _
b1000001001001001000010010110011 $
b1000001001001001000010010110011 =
b1000001001001001000010010110011 >
b1000001001001001000010010110011 M
b100 L
b10000100010 S
b10100 E
b10100 T
b10100 V
b100 @
b100 P
b100 [
b10100 R
b10000 +
b10000 F
b10000 W
1"
#20000
0"
#22000
b10000 C
b10000 I
b10000 e
b10000 f
b0 ?
b0 H
b0 O
b1 1
b1 5
b1 :
b1 N
b10 -
b10 9
b10 ;
b10 c
0(
b100100001000 d
b1000 Z
b0 &
b0 B
b0 J
b0 \
b0 Y
b0 3
b1100011 4
b0 7
b1100011 8
b11 D
b11 ]
b11 a
b11 .
b11 G
b1001000010001100011 $
b1001000010001100011 =
b1001000010001100011 >
b1001000010001100011 M
b101 L
b100100 S
b11000 E
b11000 T
b11000 V
0%
b11 A
b11 Q
b11 _
b11000 R
b10100 +
b10100 F
b10100 W
b11 @
b11 P
b11 [
1"
#24000
0"
#26000
b0 D
b0 ]
b0 a
b0 .
b0 G
b1111111111111111111111111110100 C
b1111111111111111111111111110100 I
b1111111111111111111111111110100 e
b1111111111111111111111111110100 f
1%
b0 A
b0 Q
b0 _
bz 1
bz 5
bz :
bz N
b100 -
b100 9
b100 ;
b100 c
1*
b1111111101011111111100001 d
b1 Z
b10101 Y
b0 @
b0 P
b0 [
b11111 X
b1111111 3
b111 2
b1101111 4
b111 6
b1111111 7
b1101111 8
b11111111010111111111000011101111 $
b11111111010111111111000011101111 =
b11111111010111111111000011101111 >
b11111111010111111111000011101111 M
b110 L
b1100 S
b1100 E
b1100 T
b1100 V
b11100 R
b11000 +
b11000 F
b11000 W
1"
#28000
0"
#30000
b111 D
b111 ]
b111 a
b111 .
b111 G
b1111111111101000000100000001000 C
b1111111111101000000100000001000 I
b1111111111101000000100000001000 e
b1111111111101000000100000001000 f
b11 ?
b11 H
b11 O
0%
b111 A
b111 Q
b111 _
b0 1
b0 5
b0 :
b0 N
0*
1(
b10010100000001000 d
b1000 Z
b11 &
b11 B
b11 J
b11 \
b1001 Y
b100 @
b100 P
b100 [
b1000 X
b0 3
b0 2
b110011 4
b0 6
b0 7
b110011 8
b10000 E
b10000 T
b10000 V
b100101000000010000110011 $
b100101000000010000110011 =
b100101000000010000110011 >
b100101000000010000110011 M
b11 L
b100000010100 S
b10000 R
b1100 +
b1100 F
b1100 W
1"
#32000
0"
#34000
b1001000010000010010 C
b1001000010000010010 I
b1001000010000010010 e
b1001000010000010010 f
b1 ?
b1 H
b1 O
b1 1
b1 5
b1 :
b1 N
b10 D
b10 ]
b10 a
b10 .
b10 G
b100000100100100100001001 d
b1001 Z
b1 &
b1 B
b1 J
b1 \
b10010 Y
b1001 X
b100000 3
b100000 7
0%
b10 A
b10 Q
b10 _
b1000001001001001000010010110011 $
b1000001001001001000010010110011 =
b1000001001001001000010010110011 >
b1000001001001001000010010110011 M
b100 L
b1000010000100010 S
b10100 E
b10100 T
b10100 V
b11 @
b11 P
b11 [
b10100 R
b10000 +
b10000 F
b10000 W
1"
#36000
0"
#38000
b10000 C
b10000 I
b10000 e
b10000 f
b0 ?
b0 H
b0 O
b1 1
b1 5
b1 :
b1 N
b10 -
b10 9
b10 ;
b10 c
0(
b100100001000 d
b1000 Z
b0 &
b0 B
b0 J
b0 \
b0 Y
b0 3
b1100011 4
b0 7
b1100011 8
b10 D
b10 ]
b10 a
b10 .
b10 G
b1001000010001100011 $
b1001000010001100011 =
b1001000010001100011 >
b1001000010001100011 M
b101 L
b100100 S
b11000 E
b11000 T
b11000 V
0%
b10 A
b10 Q
b10 _
b11000 R
b10100 +
b10100 F
b10100 W
b10 @
b10 P
b10 [
1"
#40000
0"
#42000
b0 D
b0 ]
b0 a
b0 .
b0 G
b1111111111111111111111111110100 C
b1111111111111111111111111110100 I
b1111111111111111111111111110100 e
b1111111111111111111111111110100 f
1%
b0 A
b0 Q
b0 _
bz 1
bz 5
bz :
bz N
b100 -
b100 9
b100 ;
b100 c
1*
b1111111101011111111100001 d
b1 Z
b10101 Y
b0 @
b0 P
b0 [
b11111 X
b1111111 3
b111 2
b1101111 4
b111 6
b1111111 7
b1101111 8
b11111111010111111111000011101111 $
b11111111010111111111000011101111 =
b11111111010111111111000011101111 >
b11111111010111111111000011101111 M
b110 L
b1100 S
b1100 E
b1100 T
b1100 V
b11100 R
b11000 +
b11000 F
b11000 W
1"
#44000
0"
#46000
b1001 D
b1001 ]
b1001 a
b1001 .
b1001 G
b1111111111101000000100000001000 C
b1111111111101000000100000001000 I
b1111111111101000000100000001000 e
b1111111111101000000100000001000 f
b10 ?
b10 H
b10 O
0%
b1001 A
b1001 Q
b1001 _
b0 1
b0 5
b0 :
b0 N
0*
1(
b10010100000001000 d
b1000 Z
b10 &
b10 B
b10 J
b10 \
b1001 Y
b111 @
b111 P
b111 [
b1000 X
b0 3
b0 2
b110011 4
b0 6
b0 7
b110011 8
b10000 E
b10000 T
b10000 V
b100101000000010000110011 $
b100101000000010000110011 =
b100101000000010000110011 >
b100101000000010000110011 M
b11 L
b100000010100 S
b10000 R
b1100 +
b1100 F
b1100 W
1"
#48000
0"
#50000
b1001000010000010010 C
b1001000010000010010 I
b1001000010000010010 e
b1001000010000010010 f
b1 ?
b1 H
b1 O
b1 1
b1 5
b1 :
b1 N
b1 D
b1 ]
b1 a
b1 .
b1 G
b100000100100100100001001 d
b1001 Z
b1 &
b1 B
b1 J
b1 \
b10010 Y
b1001 X
b100000 3
b100000 7
0%
b1 A
b1 Q
b1 _
b1000001001001001000010010110011 $
b1000001001001001000010010110011 =
b1000001001001001000010010110011 >
b1000001001001001000010010110011 M
b100 L
b1000010000100010 S
b10100 E
b10100 T
b10100 V
b10 @
b10 P
b10 [
b10100 R
b10000 +
b10000 F
b10000 W
1"
#52000
0"
#54000
b10000 C
b10000 I
b10000 e
b10000 f
b0 ?
b0 H
b0 O
b1 1
b1 5
b1 :
b1 N
0*
b10 -
b10 9
b10 ;
b10 c
0(
b100100001000 d
b1000 Z
b0 &
b0 B
b0 J
b0 \
b0 Y
b0 3
b1100011 4
b0 7
b1100011 8
b1 D
b1 ]
b1 a
b1 .
b1 G
b1001000010001100011 $
b1001000010001100011 =
b1001000010001100011 >
b1001000010001100011 M
b101 L
b100100 S
b11000 E
b11000 T
b11000 V
0%
b1 A
b1 Q
b1 _
b11000 R
b10100 +
b10100 F
b10100 W
b1 @
b1 P
b1 [
1"
#56000
0"
#58000
b0 D
b0 ]
b0 a
b0 .
b0 G
b1111111111111111111111111110100 C
b1111111111111111111111111110100 I
b1111111111111111111111111110100 e
b1111111111111111111111111110100 f
1%
b0 A
b0 Q
b0 _
bz 1
bz 5
bz :
bz N
b100 -
b100 9
b100 ;
b100 c
1*
b1111111101011111111100001 d
b1 Z
b10101 Y
b0 @
b0 P
b0 [
b11111 X
b1111111 3
b111 2
b1101111 4
b111 6
b1111111 7
b1101111 8
b11111111010111111111000011101111 $
b11111111010111111111000011101111 =
b11111111010111111111000011101111 >
b11111111010111111111000011101111 M
b110 L
b1100 S
b1100 E
b1100 T
b1100 V
b11100 R
b11000 +
b11000 F
b11000 W
1"
#60000
0"
#62000
b1010 D
b1010 ]
b1010 a
b1010 .
b1010 G
b1111111111101000000100000001000 C
b1111111111101000000100000001000 I
b1111111111101000000100000001000 e
b1111111111101000000100000001000 f
b1 ?
b1 H
b1 O
0%
b1010 A
b1010 Q
b1010 _
b0 1
b0 5
b0 :
b0 N
0*
1(
b10010100000001000 d
b1000 Z
b1 &
b1 B
b1 J
b1 \
b1001 Y
b1001 @
b1001 P
b1001 [
b1000 X
b0 3
b0 2
b110011 4
b0 6
b0 7
b110011 8
b10000 E
b10000 T
b10000 V
b100101000000010000110011 $
b100101000000010000110011 =
b100101000000010000110011 >
b100101000000010000110011 M
b11 L
b100000010100 S
b10000 R
b1100 +
b1100 F
b1100 W
1"
#64000
0"
#66000
b1001000010000010010 C
b1001000010000010010 I
b1001000010000010010 e
b1001000010000010010 f
b1 1
b1 5
b1 :
b1 N
b0 D
b0 ]
b0 a
b0 .
b0 G
b100000100100100100001001 d
b1001 Z
b10010 Y
b1001 X
b100000 3
b100000 7
1%
b0 A
b0 Q
b0 _
b1000001001001001000010010110011 $
b1000001001001001000010010110011 =
b1000001001001001000010010110011 >
b1000001001001001000010010110011 M
b100 L
b1000010000100010 S
b10100 E
b10100 T
b10100 V
b1 @
b1 P
b1 [
b10100 R
b10000 +
b10000 F
b10000 W
1"
#68000
0"
#70000
1*
b10000 C
b10000 I
b10000 e
b10000 f
b0 ?
b0 H
b0 O
b1 1
b1 5
b1 :
b1 N
b10 -
b10 9
b10 ;
b10 c
0(
b100100001000 d
b1000 Z
b0 &
b0 B
b0 J
b0 \
b0 Y
b0 3
b1100011 4
b0 7
b1100011 8
b0 D
b0 ]
b0 a
b0 .
b0 G
b1001000010001100011 $
b1001000010001100011 =
b1001000010001100011 >
b1001000010001100011 M
b101 L
b100100 S
b100100 E
b100100 T
b100100 V
1%
b0 A
b0 Q
b0 _
b11000 R
b10100 +
b10100 F
b10100 W
b0 @
b0 P
b0 [
1"
#72000
0"
#74000
bx0 C
bx0 I
bx0 e
bx0 f
bx ?
bx H
bx O
bz 1
bz 5
bz :
bz N
bx d
bx Z
bx &
bx B
bx J
bx \
bx Y
bx @
bx P
bx [
bx X
bx 3
bx 2
bx 4
bx 6
bx 7
bx 8
bx E
bx T
bx V
bx $
bx =
bx >
bx M
b1001 L
bx S
b101000 R
b100100 +
b100100 F
b100100 W
1"
#76000
0"
#78000
b0xxxxxxxxxxxxxx L
bx R
bx +
bx F
bx W
1"
