src/data_mem.v
`ifndef DATA_MEM_H
`define DATA_MEM_H

// addr here is 32 bits from BUS byt only 16 LSB bits will be used
module DataMemory(
    input wire clk,
    input wire reset,
    input wire MemWrite,
    input wire [31:0] addr,
    input wire WriteData,
    output wire [31:0] ReadData
);

// 16-bit address bus
reg [31:0] memory [2**16-1:0];
integer i;
always@(posedge clk or posedge reset) begin
    if(reset) for(i=0;i<2**16-1;i=i+1) memory[i] <= 32'd0;
    else if(MemWrite == 1'b1) memory[addr[15:0]] <= WriteData;
end
assign ReadData = memory[addr[15:0]];
endmodule

`endif

src/alu_controller.v
`ifndef ALU_CONROLLER_V
`define ALU_CONROLLER_V

module ALUController(
    input wire [6:0] opcode,
    input wire [2:0] funct3,
    input wire [6:0] funct7,
    output reg [2:0] alu_control
);

always@(*) begin
    alu_control = 7'bzzzzzzz;
    // TODO: make ALU independent of opcode, I accidentally did
    if(opcode == 7'b0110011 | opcode == 7'b0010011) begin
        case(funct3)
        3'h0: alu_control = (funct7==7'h20)?(3'b001):(3'b000); // SUB:ADD
        3'h7: alu_control = 3'b010; // AND
        3'h6: alu_control = 3'b011; // OR
        3'h4: alu_control = 3'b100; // XOR
        3'h1: alu_control = 3'b110; // SLL
        3'h5: alu_control = 3'b101; // SRL
        endcase
    end
end

endmodule

`endif

src/controller.v
`ifndef CONTROLLER_V
`define CONTROLLER_V

module Controller(
    input wire [6:0] opcode,
    input wire [6:0] funct7,
    input wire [2:0] funct3,
    input wire alu_zero,
    
    output reg RegSrc,
    output reg PCSrc,
    output reg ResultSrc,
    output reg ALUSrc,
    output reg [2:0] ImmSrc,
    output reg RegWrite,
    output reg MemWrite,
    output wire Branch
);

always@(*) begin
    case(opcode)
    7'b0110011: begin // R-Type
        RegWrite = 1'b1;
        ALUSrc = 1'b0;
        PCSrc = 1'b0;
        MemWrite = 1'b0;
        ResultSrc = 1'b0;
    end
    7'b0010011: begin
        ImmSrc = 3'b000; 
        RegWrite = 1'b1;
        ALUSrc = 1'b1;
        MemWrite = 1'b0;
        ResultSrc = 1'b0;
        PCSrc = 1'b0;
    end
    endcase
end

endmodule

`endif

src/alu.v
`ifndef ALU_V
`define ALU_V

module ALU(
    input wire [31:0] srcA, srcB,
    input wire [2:0] ALUControl,
    output wire alu_zero,
    output reg [31:0] alu_result
);

always@(*) begin
    alu_result = 32'd0;
    case(ALUControl)
    3'b000: alu_result = srcA+srcB;
    3'b001: alu_result = srcA-srcB;
    3'b010: alu_result = srcA&srcB;
    3'b011: alu_result = srcA|srcB;
    3'b100: alu_result = srcA^srcB;
    3'b101: alu_result = srcA>>srcB;
    3'b110: alu_result = srcA<<srcB;
    // 3'b111: Shift Right Arithemetic 
    endcase
end

assign alu_zero = (alu_result == 32'd0);

endmodule

`endif

src/sign_extend.v
`ifndef SIGN_EXT_V
`define SIGN_EXT_V

// Sign extension for jump instruction is ignored as of now

module SignExtend(
    input wire [31:7] instruction,
    input wire [2:0] ImmSrc,
    output wire [31:0] out
);

reg [31:0] out_t;
always@(*) begin
    out_t = 32'd0;
    case(ImmSrc)
        3'b000: // I-type
            out_t = { {20{instruction[31]}}, instruction[31:20] }; // 12 bits encoded
        3'b001: // S-type
            out_t = { {20{instruction[31]}}, instruction[31:25], instruction[4:0] };
        3'b010: // B-type, 12 bit encoded 1-12, 0th aways = 0
            out_t = { {19{instruction[31]}}, instruction[31], instruction[30:25], instruction[11:8], instruction[7], 1'b0 };
        3'b011: // U-type
            out_t = { instruction[31:12], 12'b0 };
        // 3'b100: // J-type
    endcase
end

assign out = out_t;
endmodule

`endif

src/mux.v
`ifndef MUX_V
`define MUX_V

module MUX2 #(parameter size = 32)(
    input wire [size-1:0] I0,
    input wire [size-1:0] I1,
    input wire s,
    output wire [size-1:0] out
);
assign out = s?I1:I0;
endmodule

`endif

src/reg_file.v
`ifndef REG_FILE_V
`define REG_FILE_V

module RegisterFile(
    input wire clk,
    input wire reset,
    input wire RegWrite,
    input wire [4:0] addr1,
    input wire [4:0] addr2,
    input wire [4:0] addr3,
    output wire [31:0] read1,
    output wire [31:0] read2,
    output wire [31:0] data
);

reg [31:0] registers [31:0];
integer i;
always@(posedge clk or posedge reset) begin
    if(reset) for(i=0;i<32;i=i+1) registers[i] <= 32'd0;
    else if(RegWrite) registers[addr3] <= data;
    $writememh("../bin/registers.hex", registers);
end
assign read1 = registers[addr1];
assign read2 = registers[addr2];

endmodule

`endif

src/instr_mem.v
`ifndef INSTR_MEM_V
`define INSTR_MEM_V

// PC is 16-bit
module InstructionMemory(
    input wire [15:0] addr,
    output wire [31:0] instruction
);

reg [31:0] memory [2**16-1:0];
assign instruction = memory[addr];

initial $readmemh("../examples/instructions.hex", memory, 0, 2);

endmodule

`endif

src/pc.v
`ifndef PC_V
`define PC_V

// 16-bit Program Counter
module ProgramCounter(
    input wire clk,
    input wire reset,
    input wire [15:0] pc_next,
    output reg [15:0] pc
);
always@(posedge clk or posedge reset) begin
   if(reset) pc <= 15'd0;
   else pc <= pc_next;
end
endmodule

`endif

src/datapath.v
`ifndef DATAPATH_V
`define DATAPATH_V

`include "mux.v"
`include "pc.v"
`include "instr_mem.v"
`include "reg_file.v"
`include "sign_extend.v"
`include "alu.v"

module Datapath(
    input wire clk,
    input wire reset,
    output wire [15:0] PC, // goes to instruction memory
    output wire alu_zero,
    // control inputs
    input wire RegSrc,
    input wire PCSrc,
    input wire ResultSrc,
    input wire [2:0] ALUControl,
    input wire ALUSrc,
    input wire [2:0] ImmSrc,
    input wire RegWrite,
    input wire Branch,
    input wire [31:0] ReadData,
    output wire [31:0] WriteData,
    output wire [15:0] DataAddr,
    output wire [31:0] instr
);

wire [15:0] PC_Next;

wire [31:0] instruction;
wire [31:0] alu_src_a, alu_src_b;
wire [31:0] SigmImm;
wire [31:0] alu_result;
wire [31:0] Result; // goes to wd3 (register file writing data)

// wanna use only LSB 16 bits of sigimm since pc in 16 bti
MUX2 #(.size(16)) pc_mux(
    .I0(PC[15:0]+16'd4),
    .I1(PC[15:0]+16'd4+SigmImm*4),
    .s(PCSrc),
    .out(PC_Next)
);

// use PC[15:2] to load instructions from memory
ProgramCounter progr_counter(
    .clk(clk), .reset(reset),
    .pc_next(PC_Next),
    .pc(PC)
);

InstructionMemory instr_mem(
    .addr(PC>>2),
    .instruction(instruction)
);

MUX2 #(.size(32)) result_mux(
    .I0(alu_result),
    .I1(ReadData),
    .s(ResultSrc),
    .out(Result)
);

RegisterFile reg_file(
    .clk(clk), .reset(reset),
    .RegWrite(RegWrite),
    .addr1(instruction[19:15]),
    .addr2(instruction[24:20]),
    .addr3(instruction[11:7]),
    .read1(alu_src_a),
    .read2(WriteData),
    .data(Result)
);

MUX2 #(.size(32)) alu_src_b_mux(
    .I0(WriteData),
    .I1(SigmImm),
    .s(ALUSrc),
    .out(alu_src_b)
);

SignExtend sign_ext(
    .instruction(instruction[31:7]),
    .ImmSrc(ImmSrc),
    .out(SigmImm)
);

ALU main_alu(
    .srcA(alu_src_a),
    .srcB(alu_src_b),
    .alu_zero(alu_zero),
    .alu_result(alu_result),
    .ALUControl(ALUControl)
);

assign DataAddr = alu_result[15:0];
assign instr = instruction;

endmodule

`endif

src/cpu.v
`ifndef CPU_V
`define CPU_V

`include "data_mem.v"
`include "instr_mem.v"
`include "controller.v"
`include "alu_controller.v"
`include "datapath.v"

module CPU(
    input wire clk,
    input wire reset
);

wire [15:0] PC;
wire alu_zero, RegSrc, PCSrc, ResultSrc, ALUSrc, RegWrite, Branch;
wire [2:0] ALUControl, ImmSrc;
wire [15:0] DataAddr;
wire [31:0] ReadData, WriteData;
wire [31:0] instruction;

Datapath datapath(
    .clk(clk), .reset(reset),
    .PC(PC),
    .alu_zero(alu_zero),
    .RegSrc(RegSrc),
    .PCSrc(PCSrc),
    .ResultSrc(ResultSrc),
    .ALUControl(ALUControl),
    .ALUSrc(ALUSrc),
    .ImmSrc(ImmSrc),
    .RegWrite(RegWrite),
    .Branch(Branch),
    .ReadData(ReadData),
    .WriteData(WriteData),
    .DataAddr(DataAddr),
    .instr(instruction)
);

Controller controller(
    .opcode(instruction[6:0]),
    .funct7(instruction[31:25]),
    .funct3(instruction[14:12]),
    .alu_zero(alu_zero),
    .RegSrc(RegSrc),
    .PCSrc(PCSrc),
    .ResultSrc(ResultSrc),
    .ALUSrc(ALUSrc),
    .ImmSrc(ImmSrc),
    .RegWrite(RegWrite),
    .MemWrite(MemWrite),
    .Branch(Branch)
);

ALUController alu_controller(
    .opcode(instruction[6:0]),
    .funct3(instruction[14:12]),
    .funct7(instruction[31:25]),
    .alu_control(ALUControl)
);

endmodule

`endif

src/cpu_tb.v
`timescale 1ns/1ps
`include "cpu.v"

module CPU_tb();

reg clk, reset;

CPU DUT(clk, reset);

initial begin
    $dumpfile("../bin/cpu.vcd");
    $dumpvars(0, DUT);
    clk = 0;
    reset = 1;
    #5 reset = 0;
    #500 $finish;
end

always #2 clk = ~clk;

endmodule

bin/cpu.vcd
$date
	Wed Jul 30 02:53:16 2025
$end
$version
	Icarus Verilog
$end
$timescale
	1ps
$end
$scope module CPU_tb $end
$scope module DUT $end
$var wire 1 ! Branch $end
$var wire 32 " ReadData [31:0] $end
$var wire 1 # clk $end
$var wire 1 $ reset $end
$var wire 32 % instruction [31:0] $end
$var wire 1 & alu_zero $end
$var wire 32 ' WriteData [31:0] $end
$var wire 1 ( ResultSrc $end
$var wire 1 ) RegWrite $end
$var wire 1 * RegSrc $end
$var wire 1 + PCSrc $end
$var wire 16 , PC [15:0] $end
$var wire 1 - MemWrite $end
$var wire 3 . ImmSrc [2:0] $end
$var wire 16 / DataAddr [15:0] $end
$var wire 1 0 ALUSrc $end
$var wire 3 1 ALUControl [2:0] $end
$scope module alu_controller $end
$var wire 3 2 funct3 [2:0] $end
$var wire 7 3 funct7 [6:0] $end
$var wire 7 4 opcode [6:0] $end
$var reg 3 5 alu_control [2:0] $end
$upscope $end
$scope module controller $end
$var wire 1 ! Branch $end
$var wire 3 6 funct3 [2:0] $end
$var wire 7 7 funct7 [6:0] $end
$var wire 7 8 opcode [6:0] $end
$var wire 1 & alu_zero $end
$var reg 1 0 ALUSrc $end
$var reg 3 9 ImmSrc [2:0] $end
$var reg 1 - MemWrite $end
$var reg 1 + PCSrc $end
$var reg 1 * RegSrc $end
$var reg 1 ) RegWrite $end
$var reg 1 ( ResultSrc $end
$upscope $end
$scope module datapath $end
$var wire 3 : ALUControl [2:0] $end
$var wire 1 0 ALUSrc $end
$var wire 1 ! Branch $end
$var wire 3 ; ImmSrc [2:0] $end
$var wire 1 + PCSrc $end
$var wire 32 < ReadData [31:0] $end
$var wire 1 * RegSrc $end
$var wire 1 ) RegWrite $end
$var wire 1 ( ResultSrc $end
$var wire 1 # clk $end
$var wire 32 = instr [31:0] $end
$var wire 1 $ reset $end
$var wire 32 > instruction [31:0] $end
$var wire 1 & alu_zero $end
$var wire 32 ? alu_src_b [31:0] $end
$var wire 32 @ alu_src_a [31:0] $end
$var wire 32 A alu_result [31:0] $end
$var wire 32 B WriteData [31:0] $end
$var wire 32 C SigmImm [31:0] $end
$var wire 32 D Result [31:0] $end
$var wire 16 E PC_Next [15:0] $end
$var wire 16 F PC [15:0] $end
$var wire 16 G DataAddr [15:0] $end
$scope module alu_src_b_mux $end
$var wire 1 0 s $end
$var wire 32 H out [31:0] $end
$var wire 32 I I1 [31:0] $end
$var wire 32 J I0 [31:0] $end
$var parameter 32 K size $end
$upscope $end
$scope module instr_mem $end
$var wire 16 L addr [15:0] $end
$var wire 32 M instruction [31:0] $end
$upscope $end
$scope module main_alu $end
$var wire 3 N ALUControl [2:0] $end
$var wire 32 O srcB [31:0] $end
$var wire 32 P srcA [31:0] $end
$var wire 1 & alu_zero $end
$var reg 32 Q alu_result [31:0] $end
$upscope $end
$scope module pc_mux $end
$var wire 16 R I0 [15:0] $end
$var wire 16 S I1 [15:0] $end
$var wire 1 + s $end
$var wire 16 T out [15:0] $end
$var parameter 32 U size $end
$upscope $end
$scope module progr_counter $end
$var wire 1 # clk $end
$var wire 16 V pc_next [15:0] $end
$var wire 1 $ reset $end
$var reg 16 W pc [15:0] $end
$upscope $end
$scope module reg_file $end
$var wire 1 ) RegWrite $end
$var wire 5 X addr1 [4:0] $end
$var wire 5 Y addr2 [4:0] $end
$var wire 5 Z addr3 [4:0] $end
$var wire 1 # clk $end
$var wire 32 [ read1 [31:0] $end
$var wire 32 \ read2 [31:0] $end
$var wire 1 $ reset $end
$var wire 32 ] data [31:0] $end
$var integer 32 ^ i [31:0] $end
$upscope $end
$scope module result_mux $end
$var wire 32 _ I0 [31:0] $end
$var wire 32 ` I1 [31:0] $end
$var wire 1 ( s $end
$var wire 32 a out [31:0] $end
$var parameter 32 b size $end
$upscope $end
$scope module sign_ext $end
$var wire 3 c ImmSrc [2:0] $end
$var wire 25 d instruction [31:7] $end
$var wire 32 e out [31:0] $end
$var reg 32 f out_t [31:0] $end
$upscope $end
$upscope $end
$upscope $end
$upscope $end
$enddefinitions $end
$comment Show the parameter values. $end
$dumpall
b100000 b
b10000 U
b100000 K
$end
#0
$dumpvars
b11111111 f
b11111111 e
b111111110000000001000 d
b0 c
b11111111 a
bz `
b11111111 _
b100000 ^
b11111111 ]
b0 \
b0 [
b1000 Z
b11111 Y
b0 X
b0 W
b100 V
b100 T
b10000000000 S
b100 R
b11111111 Q
b0 P
b11111111 O
b0 N
b1111111100000000010000010011 M
b0 L
b0 J
b11111111 I
b11111111 H
b11111111 G
b0 F
b100 E
b11111111 D
b11111111 C
b0 B
b11111111 A
b0 @
b11111111 ?
b1111111100000000010000010011 >
b1111111100000000010000010011 =
bz <
b0 ;
b0 :
b0 9
b10011 8
b111 7
b0 6
b0 5
b10011 4
b111 3
b0 2
b0 1
10
b11111111 /
b0 .
0-
b0 ,
0+
x*
1)
0(
b0 '
0&
b1111111100000000010000010011 %
1$
0#
bz "
z!
$end
#2000
b100000 ^
1#
#4000
0#
#5000
0$
#6000
b10000100 D
b10000100 ]
b10000100 a
b10000100 /
b10000100 G
b10000100 ?
b10000100 H
b10000100 O
b10000100 C
b10000100 I
b10000100 e
b10000100 f
0&
b10000100 A
b10000100 Q
b10000100 _
b10 1
b10 5
b10 :
b10 N
b100001000100011101001 d
b1001 Z
b100 Y
b11111111 @
b11111111 P
b11111111 [
b1000 X
b100 3
b111 2
b111 6
b100 7
b1000010001000111010010010011 %
b1000010001000111010010010011 =
b1000010001000111010010010011 >
b1000010001000111010010010011 M
b1 L
b1000011000 S
b1000 E
b1000 T
b1000 V
b1000 R
b100 ,
b100 F
b100 W
1#
#8000
0#
#10000
bx ?
bx H
bx O
b0 D
b0 ]
b0 a
b0 /
b0 G
bx C
bx I
bx e
bx f
1&
b0 A
b0 Q
b0 _
bz 1
bz 5
bz :
bz N
bx d
bx Z
bx '
bx B
bx J
bx \
bx Y
bx @
bx P
bx [
bx X
bx 3
bx 2
bx 4
bx 6
bx 7
bx 8
bx %
bx =
bx >
bx M
b10 L
bx S
b1100 E
b1100 T
b1100 V
b1100 R
b1000 ,
b1000 F
b1000 W
1#
#12000
0#
#14000
b11 L
b10000 E
b10000 T
b10000 V
b10000 R
b1100 ,
b1100 F
b1100 W
1#
#16000
0#
#18000
b100 L
b10100 E
b10100 T
b10100 V
b10100 R
b10000 ,
b10000 F
b10000 W
1#
#20000
0#
#22000
b101 L
b11000 E
b11000 T
b11000 V
b11000 R
b10100 ,
b10100 F
b10100 W
1#
#24000
0#
#26000
b110 L
b11100 E
b11100 T
b11100 V
b11100 R
b11000 ,
b11000 F
b11000 W
1#
#28000
0#
#30000
b111 L
b100000 E
b100000 T
b100000 V
b100000 R
b11100 ,
b11100 F
b11100 W
1#
#32000
0#
#34000
b1000 L
b100100 E
b100100 T
b100100 V
b100100 R
b100000 ,
b100000 F
b100000 W
1#
#36000
0#
#38000
b1001 L
b101000 E
b101000 T
b101000 V
b101000 R
b100100 ,
b100100 F
b100100 W
1#
#40000
0#
#42000
b1010 L
b101100 E
b101100 T
b101100 V
b101100 R
b101000 ,
b101000 F
b101000 W
1#
#44000
0#
#46000
b1011 L
b110000 E
b110000 T
b110000 V
b110000 R
b101100 ,
b101100 F
b101100 W
1#
#48000
0#
#50000
b1100 L
b110100 E
b110100 T
b110100 V
b110100 R
b110000 ,
b110000 F
b110000 W
1#
#52000
0#
#54000
b1101 L
b111000 E
b111000 T
b111000 V
b111000 R
b110100 ,
b110100 F
b110100 W
1#
#56000
0#
#58000
b1110 L
b111100 E
b111100 T
b111100 V
b111100 R
b111000 ,
b111000 F
b111000 W
1#
#60000
0#
#62000
b1111 L
b1000000 E
b1000000 T
b1000000 V
b1000000 R
b111100 ,
b111100 F
b111100 W
1#
#64000
0#
#66000
b10000 L
b1000100 E
b1000100 T
b1000100 V
b1000100 R
b1000000 ,
b1000000 F
b1000000 W
1#
#68000
0#
#70000
b10001 L
b1001000 E
b1001000 T
b1001000 V
b1001000 R
b1000100 ,
b1000100 F
b1000100 W
1#
#72000
0#
#74000
b10010 L
b1001100 E
b1001100 T
b1001100 V
b1001100 R
b1001000 ,
b1001000 F
b1001000 W
1#
#76000
0#
#78000
b10011 L
b1010000 E
b1010000 T
b1010000 V
b1010000 R
b1001100 ,
b1001100 F
b1001100 W
1#
#80000
0#
#82000
b10100 L
b1010100 E
b1010100 T
b1010100 V
b1010100 R
b1010000 ,
b1010000 F
b1010000 W
1#
#84000
0#
#86000
b10101 L
b1011000 E
b1011000 T
b1011000 V
b1011000 R
b1010100 ,
b1010100 F
b1010100 W
1#
#88000
0#
#90000
b10110 L
b1011100 E
b1011100 T
b1011100 V
b1011100 R
b1011000 ,
b1011000 F
b1011000 W
1#
#92000
0#
#94000
b10111 L
b1100000 E
b1100000 T
b1100000 V
b1100000 R
b1011100 ,
b1011100 F
b1011100 W
1#
#96000
0#
#98000
b11000 L
b1100100 E
b1100100 T
b1100100 V
b1100100 R
b1100000 ,
b1100000 F
b1100000 W
1#
#100000
0#
#102000
b11001 L
b1101000 E
b1101000 T
b1101000 V
b1101000 R
b1100100 ,
b1100100 F
b1100100 W
1#
#104000
0#
#106000
b11010 L
b1101100 E
b1101100 T
b1101100 V
b1101100 R
b1101000 ,
b1101000 F
b1101000 W
1#
#108000
0#
#110000
b11011 L
b1110000 E
b1110000 T
b1110000 V
b1110000 R
b1101100 ,
b1101100 F
b1101100 W
1#
#112000
0#
#114000
b11100 L
b1110100 E
b1110100 T
b1110100 V
b1110100 R
b1110000 ,
b1110000 F
b1110000 W
1#
#116000
0#
#118000
b11101 L
b1111000 E
b1111000 T
b1111000 V
b1111000 R
b1110100 ,
b1110100 F
b1110100 W
1#
#120000
0#
#122000
b11110 L
b1111100 E
b1111100 T
b1111100 V
b1111100 R
b1111000 ,
b1111000 F
b1111000 W
1#
#124000
0#
#126000
b11111 L
b10000000 E
b10000000 T
b10000000 V
b10000000 R
b1111100 ,
b1111100 F
b1111100 W
1#
#128000
0#
#130000
b100000 L
b10000100 E
b10000100 T
b10000100 V
b10000100 R
b10000000 ,
b10000000 F
b10000000 W
1#
#132000
0#
#134000
b100001 L
b10001000 E
b10001000 T
b10001000 V
b10001000 R
b10000100 ,
b10000100 F
b10000100 W
1#
#136000
0#
#138000
b100010 L
b10001100 E
b10001100 T
b10001100 V
b10001100 R
b10001000 ,
b10001000 F
b10001000 W
1#
#140000
0#
#142000
b100011 L
b10010000 E
b10010000 T
b10010000 V
b10010000 R
b10001100 ,
b10001100 F
b10001100 W
1#
#144000
0#
#146000
b100100 L
b10010100 E
b10010100 T
b10010100 V
b10010100 R
b10010000 ,
b10010000 F
b10010000 W
1#
#148000
0#
#150000
b100101 L
b10011000 E
b10011000 T
b10011000 V
b10011000 R
b10010100 ,
b10010100 F
b10010100 W
1#
#152000
0#
#154000
b100110 L
b10011100 E
b10011100 T
b10011100 V
b10011100 R
b10011000 ,
b10011000 F
b10011000 W
1#
#156000
0#
#158000
b100111 L
b10100000 E
b10100000 T
b10100000 V
b10100000 R
b10011100 ,
b10011100 F
b10011100 W
1#
#160000
0#
#162000
b101000 L
b10100100 E
b10100100 T
b10100100 V
b10100100 R
b10100000 ,
b10100000 F
b10100000 W
1#
#164000
0#
#166000
b101001 L
b10101000 E
b10101000 T
b10101000 V
b10101000 R
b10100100 ,
b10100100 F
b10100100 W
1#
#168000
0#
#170000
b101010 L
b10101100 E
b10101100 T
b10101100 V
b10101100 R
b10101000 ,
b10101000 F
b10101000 W
1#
#172000
0#
#174000
b101011 L
b10110000 E
b10110000 T
b10110000 V
b10110000 R
b10101100 ,
b10101100 F
b10101100 W
1#
#176000
0#
#178000
b101100 L
b10110100 E
b10110100 T
b10110100 V
b10110100 R
b10110000 ,
b10110000 F
b10110000 W
1#
#180000
0#
#182000
b101101 L
b10111000 E
b10111000 T
b10111000 V
b10111000 R
b10110100 ,
b10110100 F
b10110100 W
1#
#184000
0#
#186000
b101110 L
b10111100 E
b10111100 T
b10111100 V
b10111100 R
b10111000 ,
b10111000 F
b10111000 W
1#
#188000
0#
#190000
b101111 L
b11000000 E
b11000000 T
b11000000 V
b11000000 R
b10111100 ,
b10111100 F
b10111100 W
1#
#192000
0#
#194000
b110000 L
b11000100 E
b11000100 T
b11000100 V
b11000100 R
b11000000 ,
b11000000 F
b11000000 W
1#
#196000
0#
#198000
b110001 L
b11001000 E
b11001000 T
b11001000 V
b11001000 R
b11000100 ,
b11000100 F
b11000100 W
1#
#200000
0#
#202000
b110010 L
b11001100 E
b11001100 T
b11001100 V
b11001100 R
b11001000 ,
b11001000 F
b11001000 W
1#
#204000
0#
#206000
b110011 L
b11010000 E
b11010000 T
b11010000 V
b11010000 R
b11001100 ,
b11001100 F
b11001100 W
1#
#208000
0#
#210000
b110100 L
b11010100 E
b11010100 T
b11010100 V
b11010100 R
b11010000 ,
b11010000 F
b11010000 W
1#
#212000
0#
#214000
b110101 L
b11011000 E
b11011000 T
b11011000 V
b11011000 R
b11010100 ,
b11010100 F
b11010100 W
1#
#216000
0#
#218000
b110110 L
b11011100 E
b11011100 T
b11011100 V
b11011100 R
b11011000 ,
b11011000 F
b11011000 W
1#
#220000
0#
#222000
b110111 L
b11100000 E
b11100000 T
b11100000 V
b11100000 R
b11011100 ,
b11011100 F
b11011100 W
1#
#224000
0#
#226000
b111000 L
b11100100 E
b11100100 T
b11100100 V
b11100100 R
b11100000 ,
b11100000 F
b11100000 W
1#
#228000
0#
#230000
b111001 L
b11101000 E
b11101000 T
b11101000 V
b11101000 R
b11100100 ,
b11100100 F
b11100100 W
1#
#232000
0#
#234000
b111010 L
b11101100 E
b11101100 T
b11101100 V
b11101100 R
b11101000 ,
b11101000 F
b11101000 W
1#
#236000
0#
#238000
b111011 L
b11110000 E
b11110000 T
b11110000 V
b11110000 R
b11101100 ,
b11101100 F
b11101100 W
1#
#240000
0#
#242000
b111100 L
b11110100 E
b11110100 T
b11110100 V
b11110100 R
b11110000 ,
b11110000 F
b11110000 W
1#
#244000
0#
#246000
b111101 L
b11111000 E
b11111000 T
b11111000 V
b11111000 R
b11110100 ,
b11110100 F
b11110100 W
1#
#248000
0#
#250000
b111110 L
b11111100 E
b11111100 T
b11111100 V
b11111100 R
b11111000 ,
b11111000 F
b11111000 W
1#
#252000
0#
#254000
b111111 L
b100000000 E
b100000000 T
b100000000 V
b100000000 R
b11111100 ,
b11111100 F
b11111100 W
1#
#256000
0#
#258000
b1000000 L
b100000100 E
b100000100 T
b100000100 V
b100000100 R
b100000000 ,
b100000000 F
b100000000 W
1#
#260000
0#
#262000
b1000001 L
b100001000 E
b100001000 T
b100001000 V
b100001000 R
b100000100 ,
b100000100 F
b100000100 W
1#
#264000
0#
#266000
b1000010 L
b100001100 E
b100001100 T
b100001100 V
b100001100 R
b100001000 ,
b100001000 F
b100001000 W
1#
#268000
0#
#270000
b1000011 L
b100010000 E
b100010000 T
b100010000 V
b100010000 R
b100001100 ,
b100001100 F
b100001100 W
1#
#272000
0#
#274000
b1000100 L
b100010100 E
b100010100 T
b100010100 V
b100010100 R
b100010000 ,
b100010000 F
b100010000 W
1#
#276000
0#
#278000
b1000101 L
b100011000 E
b100011000 T
b100011000 V
b100011000 R
b100010100 ,
b100010100 F
b100010100 W
1#
#280000
0#
#282000
b1000110 L
b100011100 E
b100011100 T
b100011100 V
b100011100 R
b100011000 ,
b100011000 F
b100011000 W
1#
#284000
0#
#286000
b1000111 L
b100100000 E
b100100000 T
b100100000 V
b100100000 R
b100011100 ,
b100011100 F
b100011100 W
1#
#288000
0#
#290000
b1001000 L
b100100100 E
b100100100 T
b100100100 V
b100100100 R
b100100000 ,
b100100000 F
b100100000 W
1#
#292000
0#
#294000
b1001001 L
b100101000 E
b100101000 T
b100101000 V
b100101000 R
b100100100 ,
b100100100 F
b100100100 W
1#
#296000
0#
#298000
b1001010 L
b100101100 E
b100101100 T
b100101100 V
b100101100 R
b100101000 ,
b100101000 F
b100101000 W
1#
#300000
0#
#302000
b1001011 L
b100110000 E
b100110000 T
b100110000 V
b100110000 R
b100101100 ,
b100101100 F
b100101100 W
1#
#304000
0#
#306000
b1001100 L
b100110100 E
b100110100 T
b100110100 V
b100110100 R
b100110000 ,
b100110000 F
b100110000 W
1#
#308000
0#
#310000
b1001101 L
b100111000 E
b100111000 T
b100111000 V
b100111000 R
b100110100 ,
b100110100 F
b100110100 W
1#
#312000
0#
#314000
b1001110 L
b100111100 E
b100111100 T
b100111100 V
b100111100 R
b100111000 ,
b100111000 F
b100111000 W
1#
#316000
0#
#318000
b1001111 L
b101000000 E
b101000000 T
b101000000 V
b101000000 R
b100111100 ,
b100111100 F
b100111100 W
1#
#320000
0#
#322000
b1010000 L
b101000100 E
b101000100 T
b101000100 V
b101000100 R
b101000000 ,
b101000000 F
b101000000 W
1#
#324000
0#
#326000
b1010001 L
b101001000 E
b101001000 T
b101001000 V
b101001000 R
b101000100 ,
b101000100 F
b101000100 W
1#
#328000
0#
#330000
b1010010 L
b101001100 E
b101001100 T
b101001100 V
b101001100 R
b101001000 ,
b101001000 F
b101001000 W
1#
#332000
0#
#334000
b1010011 L
b101010000 E
b101010000 T
b101010000 V
b101010000 R
b101001100 ,
b101001100 F
b101001100 W
1#
#336000
0#
#338000
b1010100 L
b101010100 E
b101010100 T
b101010100 V
b101010100 R
b101010000 ,
b101010000 F
b101010000 W
1#
#340000
0#
#342000
b1010101 L
b101011000 E
b101011000 T
b101011000 V
b101011000 R
b101010100 ,
b101010100 F
b101010100 W
1#
#344000
0#
#346000
b1010110 L
b101011100 E
b101011100 T
b101011100 V
b101011100 R
b101011000 ,
b101011000 F
b101011000 W
1#
#348000
0#
#350000
b1010111 L
b101100000 E
b101100000 T
b101100000 V
b101100000 R
b101011100 ,
b101011100 F
b101011100 W
1#
#352000
0#
#354000
b1011000 L
b101100100 E
b101100100 T
b101100100 V
b101100100 R
b101100000 ,
b101100000 F
b101100000 W
1#
#356000
0#
#358000
b1011001 L
b101101000 E
b101101000 T
b101101000 V
b101101000 R
b101100100 ,
b101100100 F
b101100100 W
1#
#360000
0#
#362000
b1011010 L
b101101100 E
b101101100 T
b101101100 V
b101101100 R
b101101000 ,
b101101000 F
b101101000 W
1#
#364000
0#
#366000
b1011011 L
b101110000 E
b101110000 T
b101110000 V
b101110000 R
b101101100 ,
b101101100 F
b101101100 W
1#
#368000
0#
#370000
b1011100 L
b101110100 E
b101110100 T
b101110100 V
b101110100 R
b101110000 ,
b101110000 F
b101110000 W
1#
#372000
0#
#374000
b1011101 L
b101111000 E
b101111000 T
b101111000 V
b101111000 R
b101110100 ,
b101110100 F
b101110100 W
1#
#376000
0#
#378000
b1011110 L
b101111100 E
b101111100 T
b101111100 V
b101111100 R
b101111000 ,
b101111000 F
b101111000 W
1#
#380000
0#
#382000
b1011111 L
b110000000 E
b110000000 T
b110000000 V
b110000000 R
b101111100 ,
b101111100 F
b101111100 W
1#
#384000
0#
#386000
b1100000 L
b110000100 E
b110000100 T
b110000100 V
b110000100 R
b110000000 ,
b110000000 F
b110000000 W
1#
#388000
0#
#390000
b1100001 L
b110001000 E
b110001000 T
b110001000 V
b110001000 R
b110000100 ,
b110000100 F
b110000100 W
1#
#392000
0#
#394000
b1100010 L
b110001100 E
b110001100 T
b110001100 V
b110001100 R
b110001000 ,
b110001000 F
b110001000 W
1#
#396000
0#
#398000
b1100011 L
b110010000 E
b110010000 T
b110010000 V
b110010000 R
b110001100 ,
b110001100 F
b110001100 W
1#
#400000
0#
#402000
b1100100 L
b110010100 E
b110010100 T
b110010100 V
b110010100 R
b110010000 ,
b110010000 F
b110010000 W
1#
#404000
0#
#406000
b1100101 L
b110011000 E
b110011000 T
b110011000 V
b110011000 R
b110010100 ,
b110010100 F
b110010100 W
1#
#408000
0#
#410000
b1100110 L
b110011100 E
b110011100 T
b110011100 V
b110011100 R
b110011000 ,
b110011000 F
b110011000 W
1#
#412000
0#
#414000
b1100111 L
b110100000 E
b110100000 T
b110100000 V
b110100000 R
b110011100 ,
b110011100 F
b110011100 W
1#
#416000
0#
#418000
b1101000 L
b110100100 E
b110100100 T
b110100100 V
b110100100 R
b110100000 ,
b110100000 F
b110100000 W
1#
#420000
0#
#422000
b1101001 L
b110101000 E
b110101000 T
b110101000 V
b110101000 R
b110100100 ,
b110100100 F
b110100100 W
1#
#424000
0#
#426000
b1101010 L
b110101100 E
b110101100 T
b110101100 V
b110101100 R
b110101000 ,
b110101000 F
b110101000 W
1#
#428000
0#
#430000
b1101011 L
b110110000 E
b110110000 T
b110110000 V
b110110000 R
b110101100 ,
b110101100 F
b110101100 W
1#
#432000
0#
#434000
b1101100 L
b110110100 E
b110110100 T
b110110100 V
b110110100 R
b110110000 ,
b110110000 F
b110110000 W
1#
#436000
0#
